autstr/__init__.py
autstr/_version.py
autstr/arithmetic.py
autstr/buildin/__init__.py
autstr/buildin/automata.py
autstr/buildin/bin/buechi.autstr
autstr/buildin/bin/buechiZ.autstr
autstr/buildin/bin/mso0.autstr
autstr/buildin/presentations.py
autstr/presentations.py
autstr/sparse_automata.py
autstr/utils/__init__.py
autstr/utils/automata_tools.py
autstr/utils/logic.py
autstr/utils/misc.py
autstr-1.0.1.dist-info/LICENSE
autstr-1.0.1.dist-info/METADATA
autstr-1.0.1.dist-info/WHEEL
autstr-1.0.1.dist-info/RECORD
