Metadata-Version: 2.3
Name: autstr
Version: 1.0.1
Summary: Library for working with finitely presentable infinite structures
Author: Faried Abu Zaid
Author-email: fariedaz@gmail.com
Requires-Python: >=3.10,<3.13
Classifier: Programming Language :: Python :: 3
Classifier: Programming Language :: Python :: 3.10
Classifier: Programming Language :: Python :: 3.11
Classifier: Programming Language :: Python :: 3.12
Requires-Dist: automata-lib (>=5.0.0,<5.1.0)
Requires-Dist: black (>=23.9.1,<23.10.0)
Requires-Dist: flake8 (>=6.1.0,<6.2.0)
Requires-Dist: graphviz (>=0.21,<0.22)
Requires-Dist: ipykernel (>=6.29.5)
Requires-Dist: isort (>=5.12.0,<5.13.0)
Requires-Dist: jax (>=0.4.13)
Requires-Dist: jupyter (>=1.1.1,<2.0.0)
Requires-Dist: mypy (>=1.11.0,<1.12.0)
Requires-Dist: nltk (>=3.7,<4.0)
Requires-Dist: pre-commit (>=3.2.0,<3.3.0)
Requires-Dist: pytest (>=7.4.0,<7.5.0)
Requires-Dist: pytest-asyncio (>=0.22.0)
Requires-Dist: pytest-cov (>=4.1.0,<4.2.0)
Requires-Dist: pytest-mock (>=3.10.0,<3.11.0)
Requires-Dist: sphinx-autodoc-typehints (>=1.19.2,<1.20.0)
Requires-Dist: visual-automata (>=1.1.1,<2.0.0)
